{
  "playersRoster": [
    {
      "id": 1,
      "fullName": "Mike Westphal",
      "position": "Defense",
      "phone": "505-123-4567"
    },
    {
      "id": 2,
      "fullName": "Seth Billie",
      "position": "Goalie",
      "phone": "505-123-4568"
    },
    {
      "fullName": "Donald \"Woogie\" Gadomski",
      "position": "Goalie",
      "phone": "505-987-6541",
      "id": 6
    },
    {
      "fullName": "Brent Kvern",
      "position": "Defense",
      "phone": "505-654-3219",
      "id": 7
    },
    {
      "fullName": "Billy M. F. Cottle",
      "position": "Forward",
      "phone": "505-123-4569",
      "id": 8
    },
    {
      "fullName": "Ron Neuser",
      "position": "Goalie",
      "phone": "505-669-1234",
      "id": 9
    }
  ]
}